odoo/addons/dateutil_rrule_validator/__init__.py
odoo/addons/dateutil_rrule_validator/__manifest__.py
odoo/addons/dateutil_rrule_validator/models/__init__.py
odoo/addons/dateutil_rrule_validator/models/calendar_recurrence.py
odoo14_addon_dateutil_rrule_validator-14.0.0.1.1.dev1.dist-info/METADATA
odoo14_addon_dateutil_rrule_validator-14.0.0.1.1.dev1.dist-info/WHEEL
odoo14_addon_dateutil_rrule_validator-14.0.0.1.1.dev1.dist-info/top_level.txt
odoo14_addon_dateutil_rrule_validator-14.0.0.1.1.dev1.dist-info/RECORD
